mcp_server_qdrant_memory-0.0.1.dist-info/licenses/LICENSE
qdrant_memory_server/main.py
mcp_server_qdrant_memory-0.0.1.dist-info/METADATA
mcp_server_qdrant_memory-0.0.1.dist-info/WHEEL
mcp_server_qdrant_memory-0.0.1.dist-info/entry_points.txt
mcp_server_qdrant_memory-0.0.1.dist-info/top_level.txt
mcp_server_qdrant_memory-0.0.1.dist-info/RECORD
