Metadata-Version: 2.4
Name: mcp-server-qdrant-memory
Version: 0.0.1
Summary: MCP server for qdrant memory.
Author: kakehashi
License: MIT License
Project-URL: Homepage, https://github.com/kakehashi/mcp-server-qdrant-memory
Project-URL: Bug Tracker, https://github.com/kakehashi/mcp-server-qdrant-memory/issues
Project-URL: Documentation, https://github.com/kakehashi/mcp-server-qdrant-memory#readme
Keywords: mcp,qdrant,memory
Classifier: Development Status :: 3 - Alpha
Classifier: Intended Audience :: Developers
Classifier: License :: OSI Approved :: MIT License
Classifier: Operating System :: OS Independent
Classifier: Programming Language :: Python :: 3
Classifier: Programming Language :: Python :: 3.10
Classifier: Programming Language :: Python :: 3.11
Classifier: Programming Language :: Python :: 3.12
Classifier: Topic :: Software Development :: Libraries :: Python Modules
Requires-Python: >=3.10
License-File: LICENSE
Requires-Dist: mcp>=1.9.4
Requires-Dist: fastmcp>=2.3.0
Requires-Dist: qdrant_client>=1.14.3
Requires-Dist: sentence-transformers>=5.0.0
Provides-Extra: dev
Requires-Dist: pylint; extra == "dev"
Requires-Dist: pylint-plugin-utils; extra == "dev"
Requires-Dist: pylint-mcp; extra == "dev"
Requires-Dist: black; extra == "dev"
Provides-Extra: build
Requires-Dist: build>=1.0.0; extra == "build"
Requires-Dist: twine>=5.0.0; extra == "build"
Requires-Dist: wheel>=0.42.0; extra == "build"
Dynamic: license-file
